yanki/__init__.py
yanki/__version__.py
yanki/anki.py
yanki/errors.py
yanki/field.py
yanki/html_out.py
yanki/utils.py
yanki/video.py
yanki/cli/__init__.py
yanki/cli/decks.py
yanki/cli/server.py
yanki/parser/__init__.py
yanki/parser/config.py
yanki/parser/model.py
yanki/parser/parser.py
yanki-0.5.1.dist-info/METADATA
yanki-0.5.1.dist-info/WHEEL
yanki-0.5.1.dist-info/entry_points.txt
yanki-0.5.1.dist-info/licenses/LICENSE-APACHE
yanki-0.5.1.dist-info/licenses/LICENSE-MIT
yanki-0.5.1.dist-info/RECORD
