Metadata-Version: 2.4
Name: yanki
Version: 0.5.1
Summary: Build Anki decks from text files containing YouTube URLs.
Project-URL: Homepage, https://github.com/danielparks/yanki
Project-URL: Issues, https://github.com/danielparks/yanki/issues
Author-email: Daniel Parks <oss-yanki@demonhorse.org>
License-Expression: MIT OR Apache-2.0
License-File: LICENSE-APACHE
License-File: LICENSE-MIT
Keywords: anki,flashcards
Classifier: Development Status :: 4 - Beta
Classifier: Intended Audience :: Education
Classifier: License :: OSI Approved :: Apache Software License
Classifier: License :: OSI Approved :: MIT License
Classifier: Topic :: Education
Requires-Python: >=3.11
Requires-Dist: click<9.0,>=8.1.8
Requires-Dist: colorlog<7.0,>=6.9.0
Requires-Dist: docutils<0.22,>=0.21.2
Requires-Dist: ffmpeg-python<0.3,>=0.2.0
Requires-Dist: genanki<0.14,>=0.13.1
Requires-Dist: mistletoe>=1.4.0
Requires-Dist: yt-dlp>=2024.11.4
